iris_relay/__init__.py
iris_relay/app.py
iris_relay/client.py
iris_relay/db.py
iris_relay/gmail.py
iris_relay/saml.py
iris_relay/bin/__init__.py
iris_relay/bin/run_server.py
irisrelay-1.3.1.dist-info/LICENSE
irisrelay-1.3.1.dist-info/METADATA
irisrelay-1.3.1.dist-info/NOTICE
irisrelay-1.3.1.dist-info/WHEEL
irisrelay-1.3.1.dist-info/entry_points.txt
irisrelay-1.3.1.dist-info/top_level.txt
irisrelay-1.3.1.dist-info/RECORD
