Metadata-Version: 2.1
Name: irisrelay
Version: 1.3.1
Summary: Stateless reverse proxy for thirdparty service integration with Iris API.
Home-page: https://github.com/linkedin/iris-relay
Classifier: Development Status :: 5 - Production/Stable
Classifier: License :: OSI Approved :: BSD License
Classifier: Natural Language :: English
Classifier: Programming Language :: Python :: 3
License-File: LICENSE
License-File: NOTICE
Requires-Dist: pysaml2 (==4.5.0)
Requires-Dist: PyYAML
Requires-Dist: gevent (==21.12.0)
Requires-Dist: requests (==2.28.1)
Requires-Dist: requests-futures (==0.9.9)
Requires-Dist: google-api-python-client (==1.6.2)
Requires-Dist: SQLAlchemy (==1.3.0)
Requires-Dist: PyMySQL (==0.7.11)
Requires-Dist: oauth2client
Requires-Dist: simplejson
Requires-Dist: slackclient (==0.16)
Requires-Dist: twilio (==6.25.0)
Requires-Dist: urllib3 (==1.26.13)
Requires-Dist: falcon (==3.1.1)
Requires-Dist: ujson (==5.5.0)
Requires-Dist: irisclient (==1.3.0)
Requires-Dist: oncallclient (==1.1.0)
